infi.credentials_store-0.1.8-py2.7-nspkg.pth
infi/credentials_store/__init__.py
infi/credentials_store/__version__.py
infi/credentials_store/base.py
infi/credentials_store/cli.py
infi/credentials_store/utils.py
infi.credentials_store-0.1.8.dist-info/LICENSE
infi.credentials_store-0.1.8.dist-info/METADATA
infi.credentials_store-0.1.8.dist-info/WHEEL
infi.credentials_store-0.1.8.dist-info/entry_points.txt
infi.credentials_store-0.1.8.dist-info/namespace_packages.txt
infi.credentials_store-0.1.8.dist-info/top_level.txt
infi.credentials_store-0.1.8.dist-info/RECORD
